{
  "versionSandGameJs": "24w11a-dev",
  "versionSandSagaScript": "24w11a",
  "versionSandSagaServer": "24w11a",
  "urlSandGameJsScript": "https://files.harag.cz/www/app/sand-saga/prod/{versionSandSagaScript}/sand-game-js.umd.min.js",
  "urlSandGameJsCss": "https://files.harag.cz/www/app/sand-saga/prod/{versionSandSagaScript}/sand-game-js.css",
  "urlSandSagaScriptFormat": "https://files.harag.cz/www/app/sand-saga/prod/{versionSandSagaScript}/sand-saga_{scenario}.umd.min.js",
  "categories": [
    {
      "title": "Tutorial",
      "scenarios": [
        {
          "name": "tutorial-basics",
          "title": "Tutorial: Basics",
          "scriptingEnabled": false,
          "storeSnapshot": false
        },
        {
          "name": "tutorial-fallthrough",
          "title": "Tutorial: Fall-through Mode",
          "scriptingEnabled": false,
          "storeSnapshot": false
        },
        {
          "name": "tutorial-move",
          "title": "Tutorial: Move Tool",
          "scriptingEnabled": false,
          "storeSnapshot": false
        }
      ]
    },
    {
      "title": "Missions",
      "scenarios": [
        {
          "name": "mission-deforestation",
          "title": "Mission: Deforestation",
          "scriptingEnabled": false,
          "storeSnapshot": false
        },
        {
          "name": "mission-recultivation",
          "title": "Mission: Recultivation",
          "scriptingEnabled": false,
          "storeSnapshot": true
        }
      ]
    },
    {
      "title": "Puzzles",
      "scenarios": [
        {
          "name": "puzzle-sep-w",
          "title": "Challenge: Separation 1",
          "scriptingEnabled": false,
          "storeSnapshot": false
        },
        {
          "name": "puzzle-sep-ws",
          "title": "Challenge: Separation 2",
          "scriptingEnabled": false,
          "storeSnapshot": false
        },
        {
          "name": "puzzle-sep-s",
          "title": "Challenge: Separation 3",
          "scriptingEnabled": false,
          "storeSnapshot": false
        },
        {
          "name": "puzzle-transfer-w-1",
          "title": "Challenge: Water Transfer 1",
          "scriptingEnabled": false,
          "storeSnapshot": true
        },
        {
          "name": "puzzle-transfer-w-2",
          "title": "Challenge: Water Transfer 2",
          "scriptingEnabled": false,
          "storeSnapshot": true
        },
        {
          "name": "puzzle-transfer-s",
          "title": "Challenge: Sand Transfer",
          "scriptingEnabled": false,
          "storeSnapshot": true
        }
      ]
    },
    {
      "title": "Sandbox",
      "scenarios": [
        {
          "name": "sandbox",
          "title": "Sandbox",
          "scriptingEnabled": true,
          "storeSnapshot": false
        },
        {
          "name": "sandbox-sandscape",
          "title": "Sandbox: Sandscape",
          "scriptingEnabled": true,
          "storeSnapshot": true
        },
        {
          "name": "sandbox-rain",
          "title": "Sandbox: Rain",
          "scriptingEnabled": true,
          "storeSnapshot": false
        },
        {
          "name": "sandbox-meteors",
          "title": "Sandbox: Meteors",
          "scriptingEnabled": true,
          "storeSnapshot": false
        },
        {
          "name": "sandbox-empty",
          "title": "Sandbox: Empty",
          "scriptingEnabled": true,
          "storeSnapshot": false
        }
      ]
    }
  ]
}